autodynatrace/__about__.py
autodynatrace/__init__.py
autodynatrace/log.py
autodynatrace/sdk.py
autodynatrace/wrappers/__init__.py
autodynatrace/wrappers/utils.py
autodynatrace/wrappers/aiohttp/__init__.py
autodynatrace/wrappers/aiohttp/wrapper.py
autodynatrace/wrappers/asyncio/__init__.py
autodynatrace/wrappers/asyncio/wrapper.py
autodynatrace/wrappers/bottle/__init__.py
autodynatrace/wrappers/bottle/wrapper.py
autodynatrace/wrappers/celery/__init__.py
autodynatrace/wrappers/celery/wrapper.py
autodynatrace/wrappers/concurrent/__init__.py
autodynatrace/wrappers/concurrent/wrapper.py
autodynatrace/wrappers/confluent_kafka/__init__.py
autodynatrace/wrappers/confluent_kafka/wrapper.py
autodynatrace/wrappers/custom/__init__.py
autodynatrace/wrappers/custom/wrapper.py
autodynatrace/wrappers/cx_Oracle/__init__.py
autodynatrace/wrappers/cx_Oracle/wrapper.py
autodynatrace/wrappers/dbapi/__init__.py
autodynatrace/wrappers/django/__init__.py
autodynatrace/wrappers/django/apps.py
autodynatrace/wrappers/django/db.py
autodynatrace/wrappers/django/middlewares.py
autodynatrace/wrappers/django/utils.py
autodynatrace/wrappers/django/wrapper.py
autodynatrace/wrappers/fastapi/__init__.py
autodynatrace/wrappers/fastapi/middleware.py
autodynatrace/wrappers/fastapi/wrapper.py
autodynatrace/wrappers/flask/__init__.py
autodynatrace/wrappers/flask/wrapper.py
autodynatrace/wrappers/grpc/__init__.py
autodynatrace/wrappers/grpc/wrapper.py
autodynatrace/wrappers/paramiko/__init__.py
autodynatrace/wrappers/paramiko/wrapper.py
autodynatrace/wrappers/pika/__init__.py
autodynatrace/wrappers/pika/wrapper.py
autodynatrace/wrappers/psycopg2/__init__.py
autodynatrace/wrappers/psycopg2/wrapper.py
autodynatrace/wrappers/pymongo/__init__.py
autodynatrace/wrappers/pymongo/wrapper.py
autodynatrace/wrappers/pysnmp/__init__.py
autodynatrace/wrappers/pysnmp/wrapper.py
autodynatrace/wrappers/redis/__init__.py
autodynatrace/wrappers/redis/utils.py
autodynatrace/wrappers/redis/wrapper.py
autodynatrace-2.1.1.dist-info/METADATA
autodynatrace-2.1.1.dist-info/WHEEL
autodynatrace-2.1.1.dist-info/entry_points.txt
autodynatrace-2.1.1.dist-info/licenses/LICENSE
autodynatrace-2.1.1.dist-info/RECORD
