Metadata-Version: 2.3
Name: autodynatrace
Version: 2.1.1
Summary: Auto instrumentation for the OneAgent SDK
Project-URL: Homepage, https://github.com/dlopes7/autodynatrace
Project-URL: Issue Tracker, https://github.com/dlopes7/autodynatrace/issues
Author-email: David Lopes <david.lopes@dynatrace.com>
License-Expression: Apache-2.0
License-File: LICENSE
Classifier: Development Status :: 5 - Production/Stable
Classifier: Intended Audience :: Developers
Classifier: License :: OSI Approved
Classifier: License :: OSI Approved :: Apache Software License
Classifier: Operating System :: Microsoft :: Windows
Classifier: Operating System :: POSIX :: Linux
Classifier: Programming Language :: Python
Classifier: Programming Language :: Python :: 3
Classifier: Programming Language :: Python :: 3.6
Classifier: Programming Language :: Python :: Implementation :: CPython
Classifier: Topic :: System :: Monitoring
Requires-Python: >=3.6
Requires-Dist: autowrapt>=1.0
Requires-Dist: oneagent-sdk>=1.3.0
Requires-Dist: six>=1.10.0
Requires-Dist: wrapt>=1.11.2
